randoor/__init__.py
randoor/generator/__init__.py
randoor/generator/chest_search_room.py
randoor/generator/empty_room.py
randoor/generator/obstacle_room.py
randoor/generator/simple_search_room.py
randoor/generator_factory.py
randoor/spawner/__init__.py
randoor/spawner/geom.py
randoor/spawner/poly.py
randoor/utils.py
randoor-0.1.4.6.dist-info/WHEEL
randoor-0.1.4.6.dist-info/METADATA
randoor-0.1.4.6.dist-info/RECORD
